CprE381/Project1/proj/src/control_unit.vhd

library IEEE;
use IEEE.std_logic_1164.all;

entity control_unit is
	port(i_opcode  	  	: in std_logic_vector(5 downto 0);
	     i_funct	  	: in std_logic_vector(5 downto 0);
	     o_Ctrl_Unt		: out std_logic_vector(14 downto 0));
end control_unit;


architecture dataflow of control_unit is
signal s_RTYPE : std_logic_vector(14 downto 0);
begin


with i_funct select s_RTYPE <=
    "000111000110100"  when "100000", 
    "000000000110100"  when "100001",
    "000001000110100"  when "100100", 
    "000010100110100"  when "100111",
    "000010000110100"  when "100110",
    "000001100110100"  when "100101",
    "000011100110100"  when "101010", 
    "000011100110100"  when "101011", 
    "000100100110100"  when "000000", 
    "000100000110000"  when "000010",
    "000101000110100"  when "000011",
    "000111100110100"  when "100010",
    "000000100110100"  when "100011",
    "100000000000110"  when "001000", 
    "000000000000000"  when others;

with i_opcode select o_Ctrl_Unt <=
    s_RTYPE  	    when "000000", 
    "001111000100100"  when "001000", 

    "000000000000001"  when "010100", 

    "001000000100100"  when "001001",
    "001001000100000"  when "001100", 
    "001010000100000"  when "001110", 
    "001001100100000"  when "001101", 
    "001011100100100"  when "001010",
    "001011100100100"  when "001011",
    "001011000100100"  when "001111", 
    "000101100001100"  when "000100",
    "000110000001100"  when "000101",
    "001000010100100"  when "100011", 
    "001000001000100"  when "101011", 
    "000000000000110"  when "000010", 
    "010000000100110"  when "000011",
    "000000000000000"  when others;

end dataflow;

CprE381/Project1/proj/test/tb_control_unit.vhd



library IEEE;
use IEEE.std_logic_1164.all;
use IEEE.std_logic_textio.all;  -- For logic types I/O
use IEEE.numeric_std.all;	-- For to_usnigned
library std;
use std.env.all;                -- For hierarchical/external signals
use std.textio.all;             -- For basic I/O

--use work.STD_LOGIC_MATRIX.all;

entity tb_control_unit is
  generic(gCLK_HPER   : time := 50 ns);
end tb_control_unit;

architecture behavior of tb_control_unit is
  
  -- Calculate the clock period as twice the half-period
  constant cCLK_PER  : time := gCLK_HPER * 2;


  component control_unit
	port(i_opcode  	  	: in std_logic_vector(5 downto 0);
	     i_funct	  	: in std_logic_vector(5 downto 0);
	     o_Ctrl_Unt		: out std_logic_vector(14 downto 0));
  end component;

  -- Temporary signals to connect to the dff component.
  signal s_CLK : std_logic := '0';

  signal s_opcode    : std_logic_vector(5 downto 0) := (others => '0');
  signal s_funct     : std_logic_vector(5 downto 0) := (others => '0');
  signal s_Ctrl_Unt  : std_logic_vector(14 downto 0);
  signal expected_out: std_logic_vector(14 downto 0):= (others => '0');


begin

  DUT: control_unit 
  port map(i_opcode => s_opcode,
           i_funct => s_funct,
           o_Ctrl_Unt => s_Ctrl_Unt);

  -- This process sets the clock value (low for gCLK_HPER, then high
  -- for gCLK_HPER). Absent a "wait" command, processes restart 
  -- at the beginning once they have reached the final statement.
  P_CLK: process
  begin
    s_CLK <= '0';
    wait for gCLK_HPER;
    s_CLK <= '1';
    wait for gCLK_HPER/2;
  end process;
  
  -- Testbench process  
  P_TB: process
  begin
    -- test add
    s_opcode <= "000000";
    s_funct  <= "100000";
    expected_out <= "000111000110100";
    wait for cCLK_PER/2;

    -- test addu
    s_opcode <= "000000";
    s_funct  <= "100001";
    expected_out <= "000000000110100";
    wait for cCLK_PER/2;

    -- test and
    s_opcode <= "000000";
    s_funct  <= "100100";
    expected_out <= "000001000110100";
    wait for cCLK_PER/2;

    -- test nor
    s_opcode <= "000000";
    s_funct  <= "100111";
    expected_out <= "000010100110100";
    wait for cCLK_PER/2;

    -- test xor
    s_opcode <= "000000";
    s_funct  <= "100110";
    expected_out <= "000010000110100";
    wait for cCLK_PER/2;

    -- test or
    s_opcode <= "000000";
    s_funct  <= "100101";
    expected_out <= "000001100110100";
    wait for cCLK_PER/2;

    -- test slt
    s_opcode <= "000000";
    s_funct  <= "101010";
    expected_out <= "000011100110100";
    wait for cCLK_PER/2;

    -- test sll
    s_opcode <= "000000";
    s_funct  <= "000000";
    expected_out <= "000100100110100";
    wait for cCLK_PER/2;

    -- test srl
    s_opcode <= "000000";
    s_funct  <= "000010";
    expected_out <= "000100000110000";
    wait for cCLK_PER/2;

    -- test sra
    s_opcode <= "000000";
    s_funct  <= "000011";
    expected_out <= "000101000110100";
    wait for cCLK_PER/2;

    -- test sub
    s_opcode <= "000000";
    s_funct  <= "100010";
    expected_out <= "000111100110100";
    wait for cCLK_PER/2;

    -- test subu
    s_opcode <= "000000";
    s_funct  <= "100011";
    expected_out <= "000000100110100";
    wait for cCLK_PER/2;

    -- test addi
    s_opcode <= "001000";
    s_funct  <= "000000";
    expected_out <= "001111000100100";
    wait for cCLK_PER/2;

    -- test addiu
    s_opcode <= "001001";
    expected_out <= "001000000100100";
    wait for cCLK_PER/2;

    -- test andi
    s_opcode <= "001100";
    expected_out <= "001001000100000";
    wait for cCLK_PER/2;

    -- test xori
    s_opcode <= "001110";
    expected_out <= "001010000100000";
    wait for cCLK_PER/2;

    -- test ori
    s_opcode <= "001101";
    expected_out <= "001001100100000";
    wait for cCLK_PER/2;

    -- test slti
    s_opcode <= "001010";
    expected_out <= "001011100100100";
    wait for cCLK_PER/2;

    -- test lui
    s_opcode <= "001111";
    expected_out <= "001011000100100";
    wait for cCLK_PER/2;

    -- test beq
    s_opcode <= "000100";
    expected_out <= "000101100001100";
    wait for cCLK_PER/2;

    -- test bne
    s_opcode <= "000101";
    expected_out <= "000110000001100";
    wait for cCLK_PER/2;

    -- test lw
    s_opcode <= "100011";
    expected_out <= "001000010100100";
    wait for cCLK_PER/2;

    -- test sw
    s_opcode <= "101011";
    expected_out <= "001000001000100";
    wait for cCLK_PER/2;

    -- test j
    s_opcode <= "000010";
    expected_out <= "000000000000110";
    wait for cCLK_PER/2;

    -- test jal
    s_opcode <= "000011";
    expected_out <= "010000000100110";
    wait for cCLK_PER/2;

    -- test jr
    s_opcode <= "000000";
    s_funct  <= "001000";
    expected_out <= "100000000000110";
    wait for cCLK_PER/2;

    -- test halt
    s_opcode <= "010100";
    s_funct  <= "000000";
    expected_out <= "000000000000001";
    wait for cCLK_PER/2;

    wait;
  end process;
  
end behavior;

CprE381/Project1/control_unit.vcd
$date
	Sun Nov  6 21:35:14 2022
$end
$version
	QuestaSim Version 2022.2
$end
$timescale
	1ns
$end
$scope module tb_control_unit $end
$var wire 1 ! expected_out [14] $end
$var wire 1 " expected_out [13] $end
$var wire 1 # expected_out [12] $end
$var wire 1 $ expected_out [11] $end
$var wire 1 % expected_out [10] $end
$var wire 1 & expected_out [9] $end
$var wire 1 ' expected_out [8] $end
$var wire 1 ( expected_out [7] $end
$var wire 1 ) expected_out [6] $end
$var wire 1 * expected_out [5] $end
$var wire 1 + expected_out [4] $end
$var wire 1 , expected_out [3] $end
$var wire 1 - expected_out [2] $end
$var wire 1 . expected_out [1] $end
$var wire 1 / expected_out [0] $end
$var wire 1 0 s_CLK $end
$var wire 1 1 s_Ctrl_Unt [14] $end
$var wire 1 2 s_Ctrl_Unt [13] $end
$var wire 1 3 s_Ctrl_Unt [12] $end
$var wire 1 4 s_Ctrl_Unt [11] $end
$var wire 1 5 s_Ctrl_Unt [10] $end
$var wire 1 6 s_Ctrl_Unt [9] $end
$var wire 1 7 s_Ctrl_Unt [8] $end
$var wire 1 8 s_Ctrl_Unt [7] $end
$var wire 1 9 s_Ctrl_Unt [6] $end
$var wire 1 : s_Ctrl_Unt [5] $end
$var wire 1 ; s_Ctrl_Unt [4] $end
$var wire 1 < s_Ctrl_Unt [3] $end
$var wire 1 = s_Ctrl_Unt [2] $end
$var wire 1 > s_Ctrl_Unt [1] $end
$var wire 1 ? s_Ctrl_Unt [0] $end
$var wire 1 @ s_funct [5] $end
$var wire 1 A s_funct [4] $end
$var wire 1 B s_funct [3] $end
$var wire 1 C s_funct [2] $end
$var wire 1 D s_funct [1] $end
$var wire 1 E s_funct [0] $end
$var wire 1 F s_opcode [5] $end
$var wire 1 G s_opcode [4] $end
$var wire 1 H s_opcode [3] $end
$var wire 1 I s_opcode [2] $end
$var wire 1 J s_opcode [1] $end
$var wire 1 K s_opcode [0] $end
$upscope $end
$enddefinitions $end
#0
0!
0"
0#
1$
1%
1&
0'
0(
0)
1*
1+
0,
1-
0.
0/
00
01
02
03
14
15
16
07
08
09
1:
1;
0<
1=
0>
0?
1@
0A
0B
0C
0D
0E
0F
0G
0H
0I
0J
0K
1$
1%
1&
1*
1+
1-
1@
01
02
03
14
15
16
07
08
09
1:
1;
0<
1=
0>
0?
#50
10
0$
0%
0&
1E
04
05
06
#75
00
#100
1&
1C
0E
16
#125
10
#150
00
1%
0&
1'
1D
1E
15
06
17
#200
10
0'
0E
07
#225
00
#250
0%
1&
1'
0D
1E
05
16
17
#275
10
#300
00
1%
1B
0C
1D
0E
15
#350
10
1$
0%
0&
0@
0B
0D
14
05
06
#375
00
#400
0'
0-
1D
07
0=
#425
10
#450
00
1&
1-
1E
16
1=
#500
10
1%
1'
1@
0E
15
17
#525
00
#550
0$
0%
0&
1E
04
05
06
#575
10
#600
00
1#
1$
1%
1&
0'
0+
0@
0D
0E
1H
13
14
15
16
07
0;
#650
10
0$
0%
0&
1K
04
05
06
#675
00
#700
1&
0-
1I
0K
16
0=
#725
10
#750
00
1%
0&
1J
15
06
#800
10
0%
1&
1'
0J
1K
05
16
17
#825
00
#850
1%
1-
0I
1J
0K
15
1=
#875
10
#900
00
0'
1I
1K
07
#950
10
0#
1$
0%
1'
0*
1,
0H
0J
0K
03
14
05
17
0:
1<
#975
00
#1000
1%
0&
0'
1K
15
06
07
#1025
10
#1050
00
1#
0$
0%
1(
1*
0,
1F
0I
1J
13
04
05
18
1:
0<
#1100
10
0(
1)
0*
1H
08
19
0:
#1125
00
#1150
0#
0)
1.
0F
0H
0K
03
09
1>
#1175
10
#1200
00
1"
1*
1K
12
1:
#1250
10
1!
0"
0*
1B
0J
0K
02
04
07
0;
1>
11
0:
